crsts/__init__.py
crsts/crsts.py
crsts-2.5.3.dist-info/LICENSE
crsts-2.5.3.dist-info/METADATA
crsts-2.5.3.dist-info/WHEEL
crsts-2.5.3.dist-info/top_level.txt
crsts-2.5.3.dist-info/RECORD
